django_ai_boost/__init__.py
django_ai_boost/server_fastmcp.py
django_ai_boost-0.6.0.dist-info/METADATA
django_ai_boost-0.6.0.dist-info/WHEEL
django_ai_boost-0.6.0.dist-info/entry_points.txt
django_ai_boost-0.6.0.dist-info/licenses/LICENSE
django_ai_boost-0.6.0.dist-info/RECORD
