Metadata-Version: 2.4
Name: django-ai-boost
Version: 0.6.0
Summary: A Model Context Protocol (MCP) server for Django applications, inspired by Laravel Boost
Project-URL: Homepage, https://github.com/vintasoftware/django-ai-boost
Project-URL: Issues, https://github.com/vintasoftware/django-ai-boost/issues
Author-email: Rai Siqueira <rai93siqueira@gmail.com>
License-Expression: MIT
License-File: LICENSE
Requires-Python: >=3.12
Requires-Dist: django>=4.2
Requires-Dist: fastmcp>=2.13.3
